{
  "news": [
    {
      "image": "@drawable/banana",
      "headline": "ערך תזונתי עצום נתגלה בבננה",
      "info": "הוכח שבננות מכילות שפע של מגנזיום שמונע התכווצויות שרירים פתאומיות",
      "date": "20160822",
      "time": "1813",
      "iName": "nada",
      "picInTitle": "n"
    },
    {
      "headline": "בן-גוריון קם לתחייה צפה במדינה שהקים",
      "info": "וזינק מיד חזרה לקברו במפח נפש",
      "date": "20160822",
      "time": "1823",
      "iName": "nada",
      "picInTitle": "n"
    },
    {
      "headline": "בין ציון לציונות הרצל וולפסון ועוד",
      "info": "מאת כתבנו: יארוסלב האשק, פראג. הנה כי כן, ''הם הרגו את פרדיננד'' פתחה ואמרה המשרתת לאדון שווייק, שנפסל מן השרות הצבאי לפני כמה שנים, כיוון שוועדה רפואית של הצבא הכריזה עליו שהוא גולם ללא תקנה. מאת כתבנו: יארוסלב האשק, פראג. הנה כי כן, ''הם הרגו את פרדיננד'' פתחה ואמרה המשרתת לאדון שווייק, שנפסל מן השרות הצבאי לפני כמה שנים, כיוון שוועדה רפואית של הצבא הכריזה עליו שהוא גולם ללא תקנה. מאת כתבנו: יארוסלב האשק, פראג. הנה כי כן, ''הם הרגו את פרדיננד'' פתחה ואמרה המשרתת לאדון שווייק, שנפסל מן השרות הצבאי לפני כמה שנים, כיוון שוועדה רפואית של הצבא הכריזה עליו שהוא גולם ללא תקנה. מאת כתבנו: יארוסלב האשק, פראג. הנה כי כן, ''הם הרגו את פרדיננד'' פתחה ואמרה המשרתת לאדון שווייק, שנפסל מן השרות הצבאי לפני כמה שנים, כיוון שוועדה רפואית של הצבא הכריזה עליו שהוא גולם ללא תקנה. מאת כתבנו: יארוסלב האשק, פראג. הנה כי כן, ''הם הרגו את פרדיננד'' פתחה ואמרה המשרתת לאדון שווייק, שנפסל מן השרות הצבאי לפני כמה שנים, כיוון שוועדה רפואית של הצבא הכריזה עליו שהוא גולם ללא תקנה. מאת כתבנו: יארוסלב האשק, פראג. הנה כי כן, ''הם הרגו את פרדיננד'' פתחה ואמרה המשרתת לאדון שווייק, שנפסל מן השרות הצבאי לפני כמה שנים, כיוון שוועדה רפואית של הצבא הכריזה עליו שהוא גולם ללא תקנה. מאת כתבנו: יארוסלב האשק, פראג. הנה כי כן, ''הם הרגו את פרדיננד'' פתחה ואמרה המשרתת לאדון שווייק, שנפסל מן השרות הצבאי לפני כמה שנים, כיוון שוועדה רפואית של הצבא הכריזה עליו שהוא גולם ללא תקנה. מאת כתבנו: יארוסלב האשק, פראג. הנה כי כן, ''הם הרגו את פרדיננד'' פתחה ואמרה המשרתת לאדון שווייק, שנפסל מן השרות הצבאי לפני כמה שנים, כיוון שוועדה רפואית של הצבא הכריזה עליו שהוא גולם ללא תקנה. מאת כתבנו: יארוסלב האשק, פראג. הנה כי כן, ''הם הרגו את פרדיננד'' פתחה ואמרה המשרתת לאדון שווייק, שנפסל מן השרות הצבאי לפני כמה שנים, כיוון שוועדה רפואית של הצבא הכריזה עליו שהוא גולם ללא תקנה. מאת כתבנו: יארוסלב האשק, פראג. הנה כי כן, ''הם הרגו את פרדיננד'' פתחה ואמרה המשרתת לאדון שווייק, שנפסל מן השרות הצבאי לפני כמה שנים, כיוון שוועדה רפואית של הצבא הכריזה עליו שהוא גולם ללא תקנה. מאת כתבנו: יארוסלב האשק, פראג. הנה כי כן, ''הם הרגו את פרדיננד'' פתחה ואמרה המשרתת לאדון שווייק, שנפסל מן השרות הצבאי לפני כמה שנים, כיוון שוועדה רפואית של הצבא הכריזה עליו שהוא גולם ללא תקנה. מאת כתבנו: יארוסלב האשק, פראג. הנה כי כן, ''הם הרגו את פרדיננד'' פתחה ואמרה המשרתת לאדון שווייק, שנפסל מן השרות הצבאי לפני כמה שנים, כיוון שוועדה רפואית של הצבא הכריזה עליו שהוא גולם ללא תקנה. מאת כתבנו: יארוסלב האשק, פראג. הנה כי כן, ''הם הרגו את פרדיננד'' פתחה ואמרה המשרתת לאדון שווייק, שנפסל מן השרות הצבאי לפני כמה שנים, כיוון שוועדה רפואית של הצבא הכריזה עליו שהוא גולם ללא תקנה. מאת כתבנו: יארוסלב האשק, פראג. הנה כי כן, ''הם הרגו את פרדיננד'' פתחה ואמרה המשרתת לאדון שווייק, שנפסל מן השרות הצבאי לפני כמה שנים, כיוון שוועדה רפואית של הצבא הכריזה עליו שהוא גולם ללא תקנה. מאת כתבנו: יארוסלב האשק, פראג. הנה כי כן, ''הם הרגו את פרדיננד'' פתחה ואמרה המשרתת לאדון שווייק, שנפסל מן השרות הצבאי לפני כמה שנים, כיוון שוועדה רפואית של הצבא הכריזה עליו שהוא גולם ללא תקנה. מאת כתבנו: יארוסלב האשק, פראג. הנה כי כן, ''הם הרגו את פרדיננד'' פתחה ואמרה המשרתת לאדון שווייק, שנפסל מן השרות הצבאי לפני כמה שנים, כיוון שוועדה רפואית של הצבא הכריזה עליו שהוא גולם ללא תקנה. מאת כתבנו: יארוסלב האשק, פראג. הנה כי כן, ''הם הרגו את פרדיננד'' פתחה ואמרה המשרתת לאדון שווייק, שנפסל מן השרות הצבאי לפני כמה שנים, כיוון שוועדה רפואית של הצבא הכריזה עליו שהוא גולם ללא תקנה. מאת כתבנו: יארוסלב האשק, פראג. הנה כי כן, ''הם הרגו את פרדיננד'' פתחה ואמרה המשרתת לאדון שווייק, שנפסל מן השרות הצבאי לפני כמה שנים, כיוון שוועדה רפואית של הצבא הכריזה עליו שהוא גולם ללא תקנה. מאת כתבנו: יארוסלב האשק, פראג. הנה כי כן, ''הם הרגו את פרדיננד'' פתחה ואמרה המשרתת לאדון שווייק, שנפסל מן השרות הצבאי לפני כמה שנים, כיוון שוועדה רפואית של הצבא הכריזה עליו שהוא גולם ללא תקנה. מאת כתבנו: יארוסלב האשק, פראג. הנה כי כן, ''הם הרגו את פרדיננד'' פתחה ואמרה המשרתת לאדון שווייק, שנפסל מן השרות הצבאי לפני כמה שנים, כיוון שוועדה רפואית של הצבא הכריזה עליו שהוא גולם ללא תקנה. מאת כתבנו: יארוסלב האשק, פראג. הנה כי כן, ''הם הרגו את פרדיננד'' פתחה ואמרה המשרתת לאדון שווייק, שנפסל מן השרות הצבאי לפני כמה שנים, כיוון שוועדה רפואית של הצבא הכריזה עליו שהוא גולם ללא תקנה. מאת כתבנו: יארוסלב האשק, פראג. הנה כי כן, ''הם הרגו את פרדיננד'' פתחה ואמרה המשרתת לאדון שווייק, שנפסל מן השרות הצבאי לפני כמה שנים, כיוון שוועדה רפואית של הצבא הכריזה עליו שהוא גולם ללא תקנה. מאת כתבנו: יארוסלב האשק, פראג. הנה כי כן, ''הם הרגו את פרדיננד'' פתחה ואמרה המשרתת לאדון שווייק, שנפסל מן השרות הצבאי לפני כמה שנים, כיוון שוועדה רפואית של הצבא הכריזה עליו שהוא גולם ללא תקנה. מאת כתבנו: יארוסלב האשק, פראג. הנה כי כן, ''הם הרגו את פרדיננד'' פתחה ואמרה המשרתת לאדון שווייק, שנפסל מן השרות הצבאי לפני כמה שנים, כיוון שוועדה רפואית של הצבא הכריזה עליו שהוא גולם ללא תקנה. מאת כתבנו: יארוסלב האשק, פראג. הנה כי כן, ''הם הרגו את פרדיננד'' פתחה ואמרה המשרתת לאדון שווייק, שנפסל מן השרות הצבאי לפני כמה שנים, כיוון שוועדה רפואית של הצבא הכריזה עליו שהוא גולם ללא תקנה. מאת כתבנו: יארוסלב האשק, פראג. הנה כי כן, ''הם הרגו את פרדיננד'' פתחה ואמרה המשרתת לאדון שווייק, שנפסל מן השרות הצבאי לפני כמה שנים, כיוון שוועדה רפואית של הצבא הכריזה עליו שהוא גולם ללא תקנה. מאת כתבנו: יארוסלב האשק, פראג. הנה כי כן, ''הם הרגו את פרדיננד'' פתחה ואמרה המשרתת לאדון שווייק, שנפסל מן השרות הצבאי לפני כמה שנים, כיוון שוועדה רפואית של הצבא הכריזה עליו שהוא גולם ללא תקנה. מאת כתבנו: יארוסלב האשק, פראג. הנה כי כן, ''הם הרגו את פרדיננד'' פתחה ואמרה המשרתת לאדון שווייק, שנפסל מן השרות הצבאי לפני כמה שנים, כיוון שוועדה רפואית של הצבא הכריזה עליו שהוא גולם ללא תקנה. מאת כתבנו: יארוסלב האשק, פראג. הנה כי כן, ''הם הרגו את פרדיננד'' פתחה ואמרה המשרתת לאדון שווייק, שנפסל מן השרות הצבאי לפני כמה שנים, כיוון שוועדה רפואית של הצבא הכריזה עליו שהוא גולם ללא תקנה. מאת כתבנו: יארוסלב האשק, פראג. הנה כי כן, ''הם הרגו את פרדיננד'' פתחה ואמרה המשרתת לאדון שווייק, שנפסל מן השרות הצבאי לפני כמה שנים, כיוון שוועדה רפואית של הצבא הכריזה עליו שהוא גולם ללא תקנה. מאת כתבנו: יארוסלב האשק, פראג. הנה כי כן, ''הם הרגו את פרדיננד'' פתחה ואמרה המשרתת לאדון שווייק, שנפסל מן השרות הצבאי לפני כמה שנים, כיוון שוועדה רפואית של הצבא הכריזה עליו שהוא גולם ללא תקנה. מאת כתבנו: יארוסלב האשק, פראג. הנה כי כן, ''הם הרגו את פרדיננד'' פתחה ואמרה המשרתת לאדון שווייק, שנפסל מן השרות הצבאי לפני כמה שנים, כיוון שוועדה רפואית של הצבא הכריזה עליו שהוא גולם ללא תקנה. ",
      "date": "20160824",
      "time": "1522",
      "iName": "nada",
      "picInTitle": "n"
    },
    {
      "headline": "הנה כי כן, הם הרגו את פרדיננד",
      "info": "מאת כתבנו: יארוסלב האשק, פראג. הנה כי כן, ''הם הרגו את פרדיננד'' פתחה ואמרה המשרתת לאדון שווייק, שנפסל מן השרות הצבאי לפני כמה שנים, כיוון שוועדה רפואית של הצבא הכריזה עליו שהוא גולם ללא תקנה.",
      "date": "19140628",
      "time": "1623",
      "iName": "nada",
      "picInTitle": "n"
    }
  ]
}